livesplit_id_normalizer/__init__.py
livesplit_id_normalizer/cli.py
livesplit_id_normalizer/normalizer.py
tests/__init__.py
tests/test_cli.py
tests/test_normalizer.py
livesplit_id_normalizer-0.1.0.dist-info/LICENSE
livesplit_id_normalizer-0.1.0.dist-info/METADATA
livesplit_id_normalizer-0.1.0.dist-info/WHEEL
livesplit_id_normalizer-0.1.0.dist-info/entry_points.txt
livesplit_id_normalizer-0.1.0.dist-info/top_level.txt
livesplit_id_normalizer-0.1.0.dist-info/zip-safe
livesplit_id_normalizer-0.1.0.dist-info/RECORD
